<Database>

	<!-- Doctor's SPECIALIZATIONS -->
    <GameDBSkill ID="SKILL_DOC_SPEC_GENERAL_PSYCH">
        <AbbreviationLocID>SKILL_DOC_SPEC_GENERAL_PSYCH_DESCRIPTION</AbbreviationLocID>
        <ParentSkill>SKILL_DOC_QUALIF_GENERAL_MEDICINE</ParentSkill>
        <IconIndex>403</IconIndex>
			<CustomIconAssetRef>ASSET_PSYCH_ICON_SK</CustomIconAssetRef>
			<CustomIconLightBackgroundAssetRef>ASSET_PSYCH_ICON_SK_DARK</CustomIconLightBackgroundAssetRef>
        <ExtraLevelingPercent>100</ExtraLevelingPercent>
    </GameDBSkill>

</Database>